git_restack-1.0.0.data/data/share/man/man1/git-restack.1
git_restack-1.0.0.dist-info/pbr.json
git_restack-1.0.0.dist-info/metadata.json
git_restack-1.0.0.dist-info/entry_points.txt
git_restack-1.0.0.dist-info/top_level.txt
git_restack-1.0.0.dist-info/WHEEL
git_restack-1.0.0.dist-info/METADATA
git_restack-1.0.0.dist-info/DESCRIPTION.rst
git_restack-1.0.0.dist-info/RECORD
git_restack/cmd.py
git_restack/__init__.py
git_restack/tests/utils.py
git_restack/tests/__init__.py
git_restack/tests/test_git_restack.py
