Metadata-Version: 2.0
Name: git-restack
Version: 1.0.0
Summary: Tool to rebase a git branch
Home-page: https://docs.openstack.org/infra/git-restack/
Author: OpenStack
Author-email: openstack-infra@lists.openstack.org
License: Apache License (2.0)
Keywords: git gerrit restack
Platform: UNKNOWN
Requires-Dist: argparse
